odoo/addons/easy_my_coop_be/README.rst
odoo/addons/easy_my_coop_be/__init__.py
odoo/addons/easy_my_coop_be/__manifest__.py
odoo/addons/easy_my_coop_be/i18n/easy_my_coop_be.pot
odoo/addons/easy_my_coop_be/i18n/fr_BE.po
odoo/addons/easy_my_coop_be/models/__init__.py
odoo/addons/easy_my_coop_be/models/partner.py
odoo/addons/easy_my_coop_be/models/subscription_request.py
odoo/addons/easy_my_coop_be/readme/CONTRIBUTORS.rst
odoo/addons/easy_my_coop_be/readme/DESCRIPTION.rst
odoo/addons/easy_my_coop_be/static/description/index.html
odoo/addons/easy_my_coop_be/views/subscription_template.xml
odoo12_addon_easy_my_coop_be-12.0.1.3.0.dist-info/METADATA
odoo12_addon_easy_my_coop_be-12.0.1.3.0.dist-info/WHEEL
odoo12_addon_easy_my_coop_be-12.0.1.3.0.dist-info/top_level.txt
odoo12_addon_easy_my_coop_be-12.0.1.3.0.dist-info/RECORD
